[
    {
        "text_box": [
            99,
            30,
            190,
            110
        ],
        "text": "And now that he can do so much more...",
        "panel_id": "1",
        "type": "narration"
    },
    {
        "text_box": [
            101,
            144,
            172,
            232
        ],
        "text": "He's always been like that.",
        "panel_id": "1",
        "type": "dialogue"
    },
    {
        "text_box": [
            90,
            543,
            178,
            698
        ],
        "text": "He just... deep down, he doesn't take himself into account, y'know?",
        "panel_id": "1",
        "type": "dialogue"
    },
    {
        "text_box": [
            370,
            155,
            459,
            246
        ],
        "text": "It makes me wanna keep him at arm's length.",
        "panel_id": "2",
        "type": "thought"
    },
    {
        "text_box": [
            389,
            575,
            440,
            673
        ],
        "text": "Something doesn't feel right.",
        "panel_id": "2",
        "type": "thought"
    },
    {
        "text_box": [
            662,
            92,
            733,
            176
        ],
        "text": "...So I ended up bullying him.",
        "panel_id": "3",
        "type": "thought"
    },
    {
        "text_box": [
            636,
            579,
            707,
            684
        ],
        "text": "Back then, I ignored my own weakness...",
        "panel_id": "3",
        "type": "thought"
    },
    {
        "text_box": [
            1012,
            305,
            1075,
            414
        ],
        "text": "That's your way of trying to atone... right?",
        "panel_id": "4",
        "type": "dialogue"
    },
    {
        "text_box": [
            913,
            602,
            1017,
            713
        ],
        "text": "But now you're sincerely helping out with his training.",
        "panel_id": "4",
        "type": "dialogue"
    }
]