[
    {
        "text_box": [
            62,
            561,
            122,
            691
        ],
        "text": "SHOULD THEY ATTACK TOGETHER...",
        "panel_id": "1",
        "type": "narration"
    },
    {
        "text_box": [
            123,
            456,
            201,
            544
        ],
        "text": "...WE HAVE NO HOPE OF VICTORY.",
        "panel_id": "1",
        "type": "narration"
    },
    {
        "text_box": [
            396,
            127,
            503,
            237
        ],
        "text": "MEANING NEW ORDER'S RULES WOULD'VE WORKED ON HIM, I THINK.",
        "panel_id": "2",
        "type": "dialogue"
    },
    {
        "text_box": [
            377,
            265,
            484,
            364
        ],
        "text": "SHE COULD HAVE SPOKEN HIS NAME\u2014\"ALL FOR ONE.\"",
        "panel_id": "2",
        "type": "dialogue"
    },
    {
        "text_box": [
            382,
            585,
            472,
            717
        ],
        "text": "THEN WHY DIDN'T THEY DOUBLE-TEAM STAR?",
        "panel_id": "2",
        "type": "dialogue"
    },
    {
        "text_box": [
            589,
            30,
            727,
            143
        ],
        "text": "OF COURSE, THEY'LL DO EVERYTHING THEY CAN TO MAKE SURE THAT WON'T HAPPEN.",
        "panel_id": "3",
        "type": "dialogue"
    },
    {
        "text_box": [
            658,
            579,
            731,
            658
        ],
        "text": "TO WIN THIS WAR...",
        "panel_id": "3",
        "type": "narration"
    },
    {
        "text_box": [
            820,
            399,
            968,
            555
        ],
        "text": "...WE NEED TO GET THOSE TWO AT LEAST TEN KILOMETERS APART.",
        "panel_id": "4",
        "type": "narration"
    },
    {
        "text_box": [
            946,
            253,
            1070,
            364
        ],
        "text": "THAT'S THE BARE MINIMUM REQUIREMENT.",
        "panel_id": "4",
        "type": "narration"
    },
    {
        "text_box": [
            978,
            18,
            1037,
            122
        ],
        "text": "THAT'S RIGHT, TSUKAUCHI.",
        "panel_id": "4",
        "type": "dialogue"
    },
    {
        "text_box": [
            1101,
            173,
            1133,
            217
        ],
        "text": "FWAK",
        "panel_id": "4",
        "type": "sound_effect"
    }
]