[
    {
        "text_box": [
            113,
            8,
            222,
            196
        ],
        "text": "Like being on death's door, in total crisis.",
        "panel_id": "1",
        "type": "dialogue"
    },
    {
        "text_box": [
            95,
            364,
            180,
            532
        ],
        "text": "I've never felt that sensation.",
        "panel_id": "1",
        "type": "dialogue"
    },
    {
        "text_box": [
            17,
            262,
            28,
            297
        ],
        "text": "KRAK",
        "panel_id": "1",
        "type": "sound_effect"
    },
    {
        "text_box": [
            50,
            597,
            52,
            634
        ],
        "text": "KRAK",
        "panel_id": "1",
        "type": "sound_effect"
    },
    {
        "text_box": [
            469,
            560,
            475,
            588
        ],
        "text": "KRAK",
        "panel_id": "1",
        "type": "sound_effect"
    }
]