[
    {
        "text_box": [
            372,
            120,
            480,
            280
        ],
        "text": "Yeah, I know there's still some support for us out there, but...",
        "panel_id": "1",
        "type": "dialogue"
    },
    {
        "text_box": [
            376,
            453,
            483,
            590
        ],
        "text": "And what do we get for it? Rants, doubts, rage.",
        "panel_id": "1",
        "type": "dialogue"
    },
    {
        "text_box": [
            356,
            718,
            467,
            880
        ],
        "text": "This job's been running me ragged. I can't seem to catch a break.",
        "panel_id": "1",
        "type": "dialogue"
    },
    {
        "text_box": [
            825,
            109,
            891,
            209
        ],
        "text": "I'm sure we all did once.",
        "panel_id": "2",
        "type": "dialogue"
    },
    {
        "text_box": [
            831,
            458,
            915,
            574
        ],
        "text": "I thought I was different. Better.",
        "panel_id": "2",
        "type": "dialogue"
    },
    {
        "text_box": [
            807,
            650,
            940,
            821
        ],
        "text": "...One loud heckler easily drowns out ten fans. I've never felt like this before.",
        "panel_id": "2",
        "type": "dialogue"
    },
    {
        "text_box": [
            1277,
            69,
            1336,
            177
        ],
        "text": "Only human.",
        "panel_id": "3",
        "type": "narration"
    },
    {
        "text_box": [
            1275,
            734,
            1343,
            829
        ],
        "text": "But nah, I'm no hero.",
        "panel_id": "3",
        "type": "dialogue"
    }
]