[
    {
        "text_box": [
            98,
            166,
            187,
            289
        ],
        "text": "...If she's the one who comes for you...",
        "panel_id": "1",
        "type": "dialogue"
    },
    {
        "text_box": [
            65,
            320,
            198,
            437
        ],
        "text": "Hunting her down is one of my top priorities, but...",
        "panel_id": "1",
        "type": "dialogue"
    },
    {
        "text_box": [
            65,
            806,
            197,
            926
        ],
        "text": "She's actually a former senior colleague of mine.",
        "panel_id": "1",
        "type": "dialogue"
    },
    {
        "text_box": [
            453,
            217,
            502,
            300
        ],
        "text": "...and run.",
        "panel_id": "2",
        "type": "dialogue"
    },
    {
        "text_box": [
            433,
            776,
            479,
            951
        ],
        "text": "...Drop everything...",
        "panel_id": "2",
        "type": "dialogue"
    },
    {
        "text_box": [
            769,
            658,
            855,
            968
        ],
        "text": "MY HERO\nACADEMIA",
        "panel_id": "2",
        "type": "title"
    },
    {
        "text_box": [
            878,
            700,
            1038,
            910
        ],
        "text": "No. 312\u2014HIRED GUN\nBY KOHEI HORIKOSHI\nTRANSLATION: CALEB COOK\nLETTERING: JOHN HUNT\nHEXAMENDLE",
        "panel_id": "2",
        "type": "caption"
    },
    {
        "text_box": [
            1154,
            145,
            1213,
            271
        ],
        "text": "Yeah, it's her.",
        "panel_id": "3",
        "type": "dialogue"
    },
    {
        "text_box": [
            1144,
            355,
            1259,
            489
        ],
        "text": "Ammunition made of pink and dark-blue fibers...",
        "panel_id": "3",
        "type": "dialogue"
    }
]