[
    {
        "text_box": [
            148,
            201,
            188,
            280
        ],
        "text": "VOOM",
        "panel_id": "1",
        "type": "sound_effect"
    },
    {
        "text_box": [
            311,
            652,
            347,
            701
        ],
        "text": "VOOM",
        "panel_id": "2",
        "type": "sound_effect"
    },
    {
        "text_box": [
            503,
            724,
            569,
            827
        ],
        "text": "BRIDGE IS BEING LOWERED.",
        "panel_id": "2",
        "type": "narration"
    },
    {
        "text_box": [
            655,
            615,
            696,
            733
        ],
        "text": "COTTUS DEPLOYING.",
        "panel_id": "2",
        "type": "narration"
    },
    {
        "text_box": [
            891,
            399,
            928,
            494
        ],
        "text": "TARGETING TO KILL",
        "panel_id": "3",
        "type": "narration"
    },
    {
        "text_box": [
            1250,
            653,
            1263,
            707
        ],
        "text": "FWSH",
        "panel_id": "3",
        "type": "sound_effect"
    }
]