[
    {
        "text_box": [
            77,
            551,
            178,
            633
        ],
        "text": "EVER SINCE THE DAY...",
        "panel_id": "1",
        "type": "narration"
    },
    {
        "text_box": [
            606,
            137,
            733,
            265
        ],
        "text": "...THAT TOYA DIED AND DABI WAS BORN!!",
        "panel_id": "1",
        "type": "narration"
    },
    {
        "text_box": [
            944,
            17,
            1072,
            137
        ],
        "text": "...FOR THAT MAD HEAT, RUSHING HEADLONG TOWARD DEATH.",
        "panel_id": "2",
        "type": "narration"
    },
    {
        "text_box": [
            956,
            244,
            1038,
            361
        ],
        "text": "ALL FOR ONE, WHO SEEKS TO LIVE FOREVER...",
        "panel_id": "2",
        "type": "narration"
    },
    {
        "text_box": [
            991,
            168,
            1056,
            235
        ],
        "text": "...HAD NO USE...",
        "panel_id": "2",
        "type": "narration"
    },
    {
        "text_box": [
            891,
            424,
            1008,
            536
        ],
        "text": "...IS ENERGY BORN OF LIVING THINGS, AS THEY MOVE AND THRIVE.",
        "panel_id": "2",
        "type": "narration"
    },
    {
        "text_box": [
            905,
            611,
            926,
            680
        ],
        "text": "HEAT...",
        "panel_id": "2",
        "type": "narration"
    }
]