[
    {
        "text_box": [
            512,
            2089,
            554,
            2290
        ],
        "text": "@Color Clovers",
        "panel_id": "1",
        "type": "background"
    },
    {
        "text_box": [
            554,
            2799,
            590,
            2968
        ],
        "text": "@Nixksenpai",
        "panel_id": "1",
        "type": "background"
    },
    {
        "text_box": [
            1000,
            1798,
            1062,
            1904
        ],
        "text": "SKASH",
        "panel_id": "2",
        "type": "sound_effect"
    },
    {
        "text_box": [
            1777,
            643,
            1891,
            702
        ],
        "text": "SKASH",
        "panel_id": "3",
        "type": "sound_effect"
    },
    {
        "text_box": [
            2131,
            2152,
            2109,
            2253
        ],
        "text": "VWAAA",
        "panel_id": "4",
        "type": "sound_effect"
    }
]