[
    {
        "text_box": [
            65,
            339,
            216,
            483
        ],
        "text": "YOU SURE YOU'RE NOT MISTAKING THE MEANING OF THE WORD \"REMNANTS\"...",
        "panel_id": "1",
        "type": "dialogue"
    },
    {
        "text_box": [
            75,
            578,
            208,
            729
        ],
        "text": "SO SAD HOW WHITEBEARD'S REMNANTS HAVE LOST THEIR WAY!!",
        "panel_id": "1",
        "type": "dialogue"
    },
    {
        "text_box": [
            80,
            803,
            208,
            1009
        ],
        "text": "OH, MARCO... I THOUGHT YOU WERE BETTER THAN THIS! HELPING OUT THESE WHIPPERSNAPPERS?",
        "panel_id": "1",
        "type": "dialogue"
    },
    {
        "text_box": [
            116,
            173,
            185,
            285
        ],
        "text": "...BIG MOM?!",
        "panel_id": "2",
        "type": "dialogue"
    },
    {
        "text_box": [
            731,
            141,
            833,
            243
        ],
        "text": "DO AS YOU WILL.",
        "panel_id": "3",
        "type": "dialogue"
    },
    {
        "text_box": [
            700,
            620,
            838,
            725
        ],
        "text": "THAT'S RIGHT... DEAD MEN GIVE NO ORDERS.",
        "panel_id": "3",
        "type": "dialogue"
    },
    {
        "text_box": [
            718,
            808,
            888,
            1002
        ],
        "text": "DO YOU THINK THAT POPS' VOICE IS STILL BINDING US TO HIS WILL?",
        "panel_id": "3",
        "type": "dialogue"
    },
    {
        "text_box": [
            1011,
            91,
            1136,
            230
        ],
        "text": "TO AVENGE PEDRO!! I KNOW WHO I SAW!!!",
        "panel_id": "4",
        "type": "dialogue"
    },
    {
        "text_box": [
            964,
            620,
            1076,
            727
        ],
        "text": "CARROT!! WHERE ARE YOU GOING?!",
        "panel_id": "4",
        "type": "dialogue"
    },
    {
        "text_box": [
            1318,
            89,
            1382,
            209
        ],
        "text": "THANKS!!",
        "panel_id": "5",
        "type": "dialogue"
    },
    {
        "text_box": [
            1280,
            588,
            1368,
            723
        ],
        "text": "STRAW HAT!! GO ONWARD!!!",
        "panel_id": "5",
        "type": "dialogue"
    },
    {
        "text_box": [
            1368,
            815,
            1480,
            979
        ],
        "text": "EVERYONE WHO'S LEFT IS FREE!!",
        "panel_id": "5",
        "type": "dialogue"
    }
]