[
    {
        "text_box": [
            112,
            275,
            173,
            383
        ],
        "text": "\u30ac",
        "panel_id": "1",
        "type": "sound_effect"
    },
    {
        "text_box": [
            502,
            713,
            518,
            746
        ],
        "text": "!!!?",
        "panel_id": "1",
        "type": "dialogue"
    },
    {
        "text_box": [
            945,
            110,
            1199,
            213
        ],
        "text": "\u307e\u3055\u304b\u306e\u51ea\u306e\u5e2f\u306b\u6d77\u738b\u985e\u304c\u3044\u3063\u3071\u3044!!OP100\u8a71\u304a\u3081\u3067\u3068\u3046\u3054\u3056\u3044\u307e\u3059!!!",
        "panel_id": "2",
        "type": "narration"
    },
    {
        "text_box": [
            1332,
            90,
            1360,
            488
        ],
        "text": "\u300c\u50d5\u3068\u30ed\u30dc\u30b3\u300d\u756a\u5916\u7de8\u2026\u304a\u308f\u308a",
        "panel_id": "3",
        "type": "narration"
    }
]