[
    {
        "text_box": [
            64,
            41,
            89,
            119
        ],
        "text": "HUH?!",
        "panel_id": "1",
        "type": "dialogue"
    },
    {
        "text_box": [
            46,
            245,
            104,
            326
        ],
        "text": "AAAAH!!!",
        "panel_id": "1",
        "type": "dialogue"
    },
    {
        "text_box": [
            43,
            441,
            105,
            553
        ],
        "text": "THE CEILING'S\nGOING TO\nGIVE WAY!!!",
        "panel_id": "1",
        "type": "dialogue"
    },
    {
        "text_box": [
            115,
            682,
            171,
            735
        ],
        "text": "CRIK\nCRIK...",
        "panel_id": "1",
        "type": "sound_effect"
    },
    {
        "text_box": [
            467,
            31,
            566,
            163
        ],
        "text": "YOU'RE ALL\nSTILL IN HERE?!\nGET OUT NOW,\nWHILE YOU\nCAN!!!",
        "panel_id": "2",
        "type": "dialogue"
    },
    {
        "text_box": [
            416,
            621,
            527,
            718
        ],
        "text": "YOU...\nYOU'RE\nFROM THE\nSTRAW HAT\nCREW...!!!",
        "panel_id": "2",
        "type": "dialogue"
    },
    {
        "text_box": [
            851,
            250,
            920,
            379
        ],
        "text": "IT'S ONE\nTHING TO DIE\nIN BATTLE...",
        "panel_id": "3",
        "type": "dialogue"
    },
    {
        "text_box": [
            1016,
            35,
            1112,
            200
        ],
        "text": "...BUT THESE\nFLAMES ARE GOING\nTO KILL SCORES\nOF MEN ALL ON\nTHEIR OWN!!!",
        "panel_id": "3",
        "type": "dialogue"
    },
    {
        "text_box": [
            850,
            520,
            921,
            729
        ],
        "text": "WEEZ, WEEZ...\nHOW HAVE THE FLAMES\nSPREAD SO FAR?!",
        "panel_id": "3",
        "type": "dialogue"
    }
]