[
    {
        "text_box": [
            21,
            845,
            119,
            921
        ],
        "text": "PERFORMANCE\nFLOOR,\nSKULL\nDOME",
        "panel_id": "1",
        "type": "narration"
    },
    {
        "text_box": [
            41,
            1000,
            147,
            1074
        ],
        "text": "NO,\nNO,\nNO!!",
        "panel_id": "1",
        "type": "dialogue"
    },
    {
        "text_box": [
            210,
            859,
            270,
            956
        ],
        "text": "GYAAAA\n!!!",
        "panel_id": "1",
        "type": "sound_effect"
    },
    {
        "text_box": [
            534,
            829,
            589,
            917
        ],
        "text": "WAAAH\n!!!",
        "panel_id": "1",
        "type": "sound_effect"
    },
    {
        "text_box": [
            62,
            1166,
            139,
            1252
        ],
        "text": "I'M\nMOVING!!\nFORWARD!\nFORWARD!!",
        "panel_id": "2",
        "type": "dialogue"
    },
    {
        "text_box": [
            319,
            1169,
            391,
            1260
        ],
        "text": "YOU'RE\nGOING REAL\nFAST!! WE'LL\nCATCH UP IN",
        "panel_id": "2",
        "type": "dialogue"
    },
    {
        "text_box": [
            54,
            1318,
            131,
            1389
        ],
        "text": "THERE\nWE GO!!\nTHAT'S IT,\nMOMO!!",
        "panel_id": "2",
        "type": "dialogue"
    },
    {
        "text_box": [
            53,
            1415,
            141,
            1519
        ],
        "text": "I'M\nFLYING!!",
        "panel_id": "2",
        "type": "dialogue"
    },
    {
        "text_box": [
            468,
            250,
            463,
            344
        ],
        "text": "KABOOOM!!",
        "panel_id": "3",
        "type": "sound_effect"
    },
    {
        "text_box": [
            554,
            175,
            605,
            271
        ],
        "text": "HUH?!\nKAIDO?!!",
        "panel_id": "3",
        "type": "dialogue"
    },
    {
        "text_box": [
            713,
            51,
            762,
            158
        ],
        "text": "NO, LOOK\nCLOSER!!!",
        "panel_id": "3",
        "type": "dialogue"
    },
    {
        "text_box": [
            670,
            990,
            752,
            1094
        ],
        "text": "THAT'S\nNOT THE\nROOF!!",
        "panel_id": "3",
        "type": "dialogue"
    },
    {
        "text_box": [
            494,
            1301,
            609,
            1433
        ],
        "text": "LEFT!\nAAAAA\nAAAAAA...",
        "panel_id": "4",
        "type": "sound_effect"
    },
    {
        "text_box": [
            1055,
            208,
            1109,
            277
        ],
        "text": "LUFFY\n?!",
        "panel_id": "5",
        "type": "dialogue"
    },
    {
        "text_box": [
            1049,
            429,
            1093,
            495
        ],
        "text": "WHAT\nIS THAT\nTHING?!",
        "panel_id": "5",
        "type": "dialogue"
    },
    {
        "text_box": [
            1033,
            548,
            1117,
            639
        ],
        "text": "A\nDRAGON\n!!!",
        "panel_id": "5",
        "type": "dialogue"
    },
    {
        "text_box": [
            1074,
            863,
            1099,
            936
        ],
        "text": "HUH?!",
        "panel_id": "5",
        "type": "dialogue"
    },
    {
        "text_box": [
            1036,
            990,
            1103,
            1089
        ],
        "text": "WHAT?! A\nDIFFERENT\nDRAGON?!!",
        "panel_id": "5",
        "type": "dialogue"
    },
    {
        "text_box": [
            1052,
            1176,
            1112,
            1248
        ],
        "text": "WHAT\n?!",
        "panel_id": "5",
        "type": "dialogue"
    },
    {
        "text_box": [
            1035,
            1301,
            1119,
            1376
        ],
        "text": "YOU FOOL!!\nHOW CAN I\nFLY WITH\nMY EYES\nOPEN?!",
        "panel_id": "5",
        "type": "dialogue"
    },
    {
        "text_box": [
            1038,
            1398,
            1109,
            1495
        ],
        "text": "HEY, ARE YOU\nEVEN LOOKING\nWHERE WE'RE\nGOING?!",
        "panel_id": "5",
        "type": "dialogue"
    },
    {
        "text_box": [
            741,
            1340,
            753,
            1387
        ],
        "text": "BAM!!",
        "panel_id": "6",
        "type": "sound_effect"
    },
    {
        "text_box": [
            782,
            1276,
            859,
            1335
        ],
        "text": "I SEE\nSHAPES\nON THE\nROOF!!",
        "panel_id": "6",
        "type": "dialogue"
    },
    {
        "text_box": [
            778,
            1431,
            859,
            1497
        ],
        "text": "OKAY,\nTHERE'S\nONIGA-\nSHIMA!!",
        "panel_id": "6",
        "type": "dialogue"
    },
    {
        "text_box": [
            812,
            1166,
            856,
            1241
        ],
        "text": "TH... THE\nROOF?!",
        "panel_id": "6",
        "type": "dialogue"
    }
]