[
    {
        "text_box": [
            78,
            108,
            154,
            259
        ],
        "text": "...will annex the independent land of Wano!!",
        "panel_id": "1",
        "type": "narration"
    },
    {
        "text_box": [
            68,
            690,
            162,
            821
        ],
        "text": "It's been decided that the World Government...",
        "panel_id": "1",
        "type": "narration"
    },
    {
        "text_box": [
            263,
            83,
            352,
            227
        ],
        "text": "The ships are already on their way, but how likely is it that they'll be needed?",
        "panel_id": "1",
        "type": "narration"
    },
    {
        "text_box": [
            525,
            104,
            595,
            190
        ],
        "text": "Present: 12,000 vs 8,000",
        "panel_id": "2",
        "type": "narration"
    },
    {
        "text_box": [
            533,
            579,
            600,
            688
        ],
        "text": "Pre-battle: 30,000 vs 5,400",
        "panel_id": "2",
        "type": "narration"
    },
    {
        "text_box": [
            686,
            77,
            761,
            195
        ],
        "text": "Honestly, this skirmish has been gripping...",
        "panel_id": "2",
        "type": "narration"
    },
    {
        "text_box": [
            699,
            683,
            756,
            829
        ],
        "text": "That's basically stooping to the pirates' level...",
        "panel_id": "2",
        "type": "narration"
    },
    {
        "text_box": [
            882,
            160,
            952,
            269
        ],
        "text": "There's one more order...",
        "panel_id": "3",
        "type": "dialogue"
    },
    {
        "text_box": [
            882,
            360,
            941,
            468
        ],
        "text": "I'll await your report...",
        "panel_id": "3",
        "type": "dialogue"
    },
    {
        "text_box": [
            899,
            458,
            945,
            576
        ],
        "text": "...Neither can I.",
        "panel_id": "3",
        "type": "dialogue"
    },
    {
        "text_box": [
            858,
            654,
            956,
            836
        ],
        "text": "But the odds of them actually beating Kaido...? I can't even picture it happening!",
        "panel_id": "3",
        "type": "dialogue"
    },
    {
        "text_box": [
            1196,
            62,
            1248,
            164
        ],
        "text": "It concerns the Straw Hat Crew.",
        "panel_id": "3",
        "type": "narration"
    }
]