[
    {
        "text_box": [
            140,
            459,
            163,
            518
        ],
        "text": "Oh...",
        "panel_id": "1",
        "type": "dialogue"
    },
    {
        "text_box": [
            166,
            839,
            248,
            930
        ],
        "text": "My, it's starting to cloud over...",
        "panel_id": "1",
        "type": "dialogue"
    },
    {
        "text_box": [
            846,
            42,
            911,
            116
        ],
        "text": "Oh no!!",
        "panel_id": "2",
        "type": "dialogue"
    },
    {
        "text_box": [
            907,
            878,
            976,
            949
        ],
        "text": "Huh?!",
        "panel_id": "2",
        "type": "dialogue"
    },
    {
        "text_box": [
            1195,
            309,
            1236,
            357
        ],
        "text": "Master...",
        "panel_id": "3",
        "type": "dialogue"
    },
    {
        "text_box": [
            1252,
            66,
            1323,
            156
        ],
        "text": "Yu... ...no",
        "panel_id": "3",
        "type": "dialogue"
    }
]