[
    {
        "text_box": [
            48,
            679,
            76,
            704
        ],
        "text": "I PLAN TO...",
        "panel_id": "1",
        "type": "narration"
    },
    {
        "text_box": [
            251,
            479,
            384,
            664
        ],
        "text": "...had watched all sorts of magic swordsmen.",
        "panel_id": "1",
        "type": "narration"
    },
    {
        "text_box": [
            656,
            104,
            827,
            272
        ],
        "text": "...to the movements of the knights he'd fought against, or alongside...",
        "panel_id": "2",
        "type": "narration"
    },
    {
        "text_box": [
            627,
            900,
            753,
            1028
        ],
        "text": "In order to get even a little closer...",
        "panel_id": "2",
        "type": "narration"
    },
    {
        "text_box": [
            1072,
            116,
            1246,
            218
        ],
        "text": "It's no match for powerful magic, but...",
        "panel_id": "3",
        "type": "narration"
    },
    {
        "text_box": [
            1225,
            468,
            1475,
            585
        ],
        "text": "No matter how well-trained it is, the physical body has limits.",
        "panel_id": "3",
        "type": "narration"
    },
    {
        "text_box": [
            1268,
            609,
            1472,
            752
        ],
        "text": "The whole time, even after obtaining the power of anti-magic.",
        "panel_id": "3",
        "type": "narration"
    },
    {
        "text_box": [
            1049,
            910,
            1158,
            1040
        ],
        "text": "...He'd kept on training himself physically.",
        "panel_id": "3",
        "type": "narration"
    }
]